covid_vaccine_stat/__init__.py
covid_vaccine_stat/_conf.py
covid_vaccine_stat/async_request.py
covid_vaccine_stat/error.py
covid_vaccine_stat/model.py
covid_vaccine_stat/sync_request.py
covid_vaccine_stat/util.py
covid_vaccine_stat-0.0.2.dist-info/LICENSE
covid_vaccine_stat-0.0.2.dist-info/METADATA
covid_vaccine_stat-0.0.2.dist-info/WHEEL
covid_vaccine_stat-0.0.2.dist-info/top_level.txt
covid_vaccine_stat-0.0.2.dist-info/RECORD
