Metadata-Version: 2.1
Name: covid-vaccine-stat
Version: 0.0.2
Summary: 
Home-page: https://github.com/zeroday0619/covid_vaccine_stat
Author: zeroday0619
License: MIT
Project-URL: Issue tracker, https://github.com/zeroday0619/covid_vaccine_stat/issues
Platform: UNKNOWN
Classifier: Development Status :: 5 - Production/Stable
Classifier: Natural Language :: Korean
Classifier: Intended Audience :: Developers
Classifier: License :: OSI Approved :: MIT License
Classifier: Operating System :: OS Independent
Classifier: Programming Language :: Python :: 3.7
Classifier: Programming Language :: Python :: 3.8
Classifier: Programming Language :: Python :: 3.9
Classifier: Topic :: Software Development :: Libraries
Classifier: Topic :: Software Development :: Libraries :: Python Modules
Requires-Python: >=3.7.0
Requires-Dist: pydantic (>=1.8.1)
Requires-Dist: ujson (>=4.0.2)
Requires-Dist: aiohttp (>=3.7.4.post0)
Requires-Dist: requests (>=2.25.1)
